neetbox/__init__.py
neetbox/_protocol.py
neetbox/cli/flfs/ansiregular.flf
neetbox/cli/flfs/ansishadow.flf
neetbox/cli/flfs/isometrixc2.flf
neetbox/cli/flfs/nscripts.flf
neetbox/cli/flfs/nvscript.flf
neetbox/cli/parse.py
neetbox/client/__init__.py
neetbox/client/_client.py
neetbox/client/_client_web_apis.py
neetbox/client/_shell.py
neetbox/client/_signal_and_slot.py
neetbox/client/apis/_action.py
neetbox/client/apis/_image.py
neetbox/client/apis/_progress.py
neetbox/client/apis/_scalar.py
neetbox/config/__init__.py
neetbox/config/abc.py
neetbox/config/project/__init__.py
neetbox/config/user/__init__.py
neetbox/config/user/hooks.py
neetbox/extension/__init__.py
neetbox/extension/machine/__init__.py
neetbox/extension/machine/_gputil.py
neetbox/extension/machine/hardware.py
neetbox/extension/machine/platform.py
neetbox/extension/torch/arch/canny.py
neetbox/extension/torch/arch/cnn.py
neetbox/extension/torch/arch/kernels.py
neetbox/extension/torch/arch/mask_boundary_finder.py
neetbox/extension/torch/nlp.py
neetbox/extension/torch/nn/functional.py
neetbox/extension/torch/profile.py
neetbox/extension/transformers/callback.py
neetbox/frontend_dist/index.html
neetbox/frontend_dist/logo.svg
neetbox/frontend_dist/static/css/index.1baf86d7.css
neetbox/frontend_dist/static/font/KaTeX_AMS-Regular.41ddf33f.woff2
neetbox/frontend_dist/static/font/KaTeX_AMS-Regular.54112b78.ttf
neetbox/frontend_dist/static/font/KaTeX_AMS-Regular.c9039c79.woff
neetbox/frontend_dist/static/font/KaTeX_Caligraphic-Bold.21ba9ea2.ttf
neetbox/frontend_dist/static/font/KaTeX_Caligraphic-Regular.7eb57e48.ttf
neetbox/frontend_dist/static/font/KaTeX_Fraktur-Bold.6fb47ced.woff2
neetbox/frontend_dist/static/font/KaTeX_Fraktur-Bold.d87e9ab0.ttf
neetbox/frontend_dist/static/font/KaTeX_Fraktur-Bold.fa546677.woff
neetbox/frontend_dist/static/font/KaTeX_Fraktur-Regular.0c126cd4.woff
neetbox/frontend_dist/static/font/KaTeX_Fraktur-Regular.3d656863.woff2
neetbox-0.6.0.dist-info/LICENSE
neetbox-0.6.0.dist-info/METADATA
neetbox-0.6.0.dist-info/WHEEL
neetbox-0.6.0.dist-info/entry_points.txt
neetbox-0.6.0.dist-info/RECORD
