Metadata-Version: 2.3
Name: neetbox
Version: 0.6.0
Summary: Logging/Debugging/Tracing/Managing/Facilitating long running python projects, especially a replacement of tensorboard for deep learning projects
License: MIT
Keywords: computer vision,tools,logging
Author: VisualDust
Author-email: gavin@gong.host
Maintainer: PaperCube
Maintainer-email: imzhy@hotmail.com
Requires-Python: >=3.10,<4.0
Classifier: Development Status :: 4 - Beta
Classifier: License :: OSI Approved :: MIT License
Classifier: Programming Language :: Python
Classifier: Programming Language :: Python :: 3
Classifier: Programming Language :: Python :: 3.10
Classifier: Programming Language :: Python :: 3.11
Classifier: Programming Language :: Python :: 3.12
Classifier: Programming Language :: Python :: 3.13
Classifier: Topic :: Scientific/Engineering :: Visualization
Classifier: Topic :: Software Development :: Testing
Classifier: Topic :: System :: Logging
Classifier: Topic :: Utilities
Requires-Dist: click (>=8.1.7,<9.0.0)
Requires-Dist: fastapi (>=0.115.0,<0.116.0)
Requires-Dist: httpx (>=0.27.0,<0.28.0)
Requires-Dist: numpy (>=2.2.4,<3.0.0)
Requires-Dist: psutil (>=7.0.0,<8.0.0)
Requires-Dist: pyfiglet (>=1.0.2,<2.0.0)
Requires-Dist: pyjwt (>=2.8.0,<3.0.0)
Requires-Dist: python-multipart (>=0.0.12,<0.0.13)
Requires-Dist: rich (>=13)
Requires-Dist: setproctitle (>=1.0)
Requires-Dist: sqlmodel (>=0.0.24,<0.0.25)
Requires-Dist: toml (>0.10)
Requires-Dist: uvicorn (>=0.32.0,<0.33.0)
Requires-Dist: vdtoys (>=0.1.2,<0.2.0)
Requires-Dist: websocket-client (>=1.6.4,<2.0.0)
Requires-Dist: websockets (>=15.0.0,<16.0.0)
Project-URL: Homepage, https://neetbox.550w.host
Project-URL: Repository, https://github.com/visualDust/neetbox
